endereco/__init__.py
endereco-0.0.6.dist-info/LICENSE
endereco-0.0.6.dist-info/METADATA
endereco-0.0.6.dist-info/WHEEL
endereco-0.0.6.dist-info/top_level.txt
endereco-0.0.6.dist-info/RECORD
