Metadata-Version: 2.1
Name: endereco
Version: 0.0.6
Summary: Consulte CEPs via WebService dos correios
Home-page: https://github.com/claudiotorresarbe/endereco
Author: Cláudio Torres Arbe
Author-email: claudiotarbe@gmail.com
License: UNKNOWN
Platform: UNKNOWN
Classifier: Programming Language :: Python :: 3.9
Classifier: License :: OSI Approved :: MIT License
Classifier: Operating System :: OS Independent
Requires-Python: >=3.9
License-File: LICENSE
Requires-Dist: requests (<=2.27.1)
